Metadata-Version: 2.1
Name: django-magento
Version: 1.2.0
Summary: Magento integration
Home-page: https://gitlab.com/linets/ecommerce/oms/integrations/oms-magento/
Author: Linets team
Author-email: avelasqueza@linets.cl
License: MIT
Platform: UNKNOWN
Requires-Python: >=3.7
